{
    "1": {
        "id": 1,
        "description": "Lunch",
        "amount": 20.0,
        "date": "Feb-05-2025  04:53 PM"
    },
    "2": {
        "id": 2,
        "description": "Dinner",
        "amount": 10.0,
        "date": "Feb-05-2025  04:53 PM"
    },
    "4": {
        "id": 4,
        "description": "Shoes",
        "amount": 50.0,
        "date": "Jan-05-2025  04:53 PM"
    },
    "5": {
        "id": 5,
        "description": "Backpack",
        "amount": 30.0,
        "date": "Jan-08-2025  05:53 PM"
    }
}